triangular_grid_merge/__init__.py
triangular_grid_merge/edge.py
triangular_grid_merge/face.py
triangular_grid_merge/grid.py
triangular_grid_merge/merge.py
triangular_grid_merge/node.py
triangular_grid_merge/tecplot.py
triangular_grid_merge/zone.py
triangular_grid_merge-1.0.0.dist-info/LICENSE
triangular_grid_merge-1.0.0.dist-info/METADATA
triangular_grid_merge-1.0.0.dist-info/WHEEL
triangular_grid_merge-1.0.0.dist-info/top_level.txt
triangular_grid_merge-1.0.0.dist-info/RECORD
