Metadata-Version: 2.1
Name: triangular-grid-merge
Version: 1.0.0
Summary: Easy generate, read, merge and print tecplot triangular grids.
Home-page: https://github.com/SergeiShumilin/triangle-grid-merge
Author: Example Author
Author-email: ishumili@gmail.com
License: UNKNOWN
Download-URL: https://github.com/SergeiShumilin/triangle-grid-merge/archive/v1.0.0.tar.gz
Platform: UNKNOWN
Classifier: Programming Language :: Python :: 3
Classifier: License :: OSI Approved :: GNU Lesser General Public License v3 (LGPLv3)
Classifier: Operating System :: OS Independent
